pradh_ml_lab/__init__.py
pradh_ml_lab/exercise1.py
pradh_ml_lab-0.1.dist-info/METADATA
pradh_ml_lab-0.1.dist-info/WHEEL
pradh_ml_lab-0.1.dist-info/top_level.txt
pradh_ml_lab-0.1.dist-info/RECORD
