Metadata-Version: 2.4
Name: pradh_ml_lab
Version: 0.1
Summary: ML Lab Exercises Package
Author: Pradhanya
Requires-Python: >=3.6
Requires-Dist: scikit-learn
Dynamic: author
Dynamic: requires-dist
Dynamic: requires-python
Dynamic: summary
